youtube_uploader_selenium/Constant.py
youtube_uploader_selenium/__init__.py
youtube_uploader_selenium-0.1.0.dist-info/LICENSE
youtube_uploader_selenium-0.1.0.dist-info/METADATA
youtube_uploader_selenium-0.1.0.dist-info/WHEEL
youtube_uploader_selenium-0.1.0.dist-info/top_level.txt
youtube_uploader_selenium-0.1.0.dist-info/RECORD
