Metadata-Version: 2.1
Name: youtube-uploader-selenium
Version: 0.1.0
Summary: The package that helps to upload videos on YouTube using Selenium
Home-page: https://github.com/linouk23/youtube_uploader_selenium
Author: Kostya Linou
Author-email: linouk23@gmail.com
License: UNKNOWN
Platform: UNKNOWN
Classifier: Programming Language :: Python :: 3
Classifier: License :: OSI Approved :: MIT License
Classifier: Operating System :: OS Independent
Requires-Python: >=3.6
